{
  "version": "0.5.0",
  "backend_url": "https://fishingteam.su",
  "built_at": "2026-06-06",
  "platforms": {
    "windows": {
      "label": "Windows",
      "artifact": "GreyCardinalAgent.exe",
      "url": "/downloads/GreyCardinalAgent.exe",
      "format": "EXE (portable, без установки)",
      "status": "available",
      "status_label": "ready",
      "size": "33 MB",
      "size_bytes": 34386866,
      "sha256": "63861ABB6EEFC6A79C4E027C079E2EDC77B1054767B3A092CA88E7D82BFD59B3",
      "capture": "Микрофон (WASAPI), трей-агент",
      "support": "Windows x64"
    },
    "macos": {
      "label": "macOS",
      "artifact": "grey-cardinal-daemon-macos-universal.dmg",
      "url": "/downloads/grey-cardinal-daemon-macos-universal.dmg",
      "format": "DMG / PKG",
      "status": "preview",
      "status_label": "CI artifact planned",
      "size": "not published",
      "sha256": "",
      "capture": "ScreenCaptureKit / microphone",
      "support": "Apple Silicon / Intel"
    },
    "linux": {
      "label": "Linux",
      "artifact": "grey-cardinal-daemon-linux-amd64.deb",
      "url": "/downloads/grey-cardinal-daemon-linux-amd64.deb",
      "format": "DEB package",
      "status": "preview",
      "status_label": "CI artifact planned",
      "size": "not published",
      "sha256": "",
      "capture": "PipeWire / PulseAudio",
      "support": "Debian / Ubuntu amd64"
    }
  }
}
